czkawka-0.1.2.dist-info/METADATA
czkawka-0.1.2.dist-info/WHEEL
czkawka-0.1.2.dist-info/licenses/LICENSE
czkawka/__init__.py
czkawka/_czkawka.cpython-311-arm-linux-gnueabihf.so
czkawka-0.1.2.dist-info/RECORD
