Metadata-Version: 2.4
Name: czkawka
Version: 0.1.2
Classifier: Intended Audience :: Developers
Classifier: License :: OSI Approved :: MIT License
Classifier: Programming Language :: Rust
Classifier: Programming Language :: Python :: Implementation :: CPython
Classifier: Operating System :: OS Independent
Classifier: Programming Language :: Python :: 3
Classifier: Programming Language :: Python :: 3.10
Classifier: Programming Language :: Python :: 3.11
Classifier: Programming Language :: Python :: 3.12
Classifier: Programming Language :: Python :: 3.13
Classifier: Programming Language :: Python :: 3.14
Classifier: Programming Language :: Python :: 3.8
Classifier: Programming Language :: Python :: 3.9
License-File: LICENSE
Summary: Python bindings for the Czkawka Rust library, a fast image similarity engine
Keywords: image,similarity,rust,deduplication,perceptual-hash
Author-email: Louis Maddox <louismmx@gmail.com>
Requires-Python: >=3.8
Project-URL: Homepage, https://github.com/lmmx/czkawka
Project-URL: Repository, https://github.com/lmmx/czkawka.git
